CHANGES.txt
LICENSE.txt
MANIFEST.in
README.txt
setup.py
src/p01/__init__.py
src/p01.neo4jstub.egg-info/PKG-INFO
src/p01.neo4jstub.egg-info/SOURCES.txt
src/p01.neo4jstub.egg-info/dependency_links.txt
src/p01.neo4jstub.egg-info/namespace_packages.txt
src/p01.neo4jstub.egg-info/not-zip-safe
src/p01.neo4jstub.egg-info/requires.txt
src/p01.neo4jstub.egg-info/top_level.txt
src/p01/neo4jstub/README.txt
src/p01/neo4jstub/__init__.py
src/p01/neo4jstub/testing.py
src/p01/neo4jstub/conf/README.txt
src/p01/neo4jstub/conf/logging.properties
src/p01/neo4jstub/conf/neo4j-http-logging.xml
src/p01/neo4jstub/conf/neo4j-server.properties
src/p01/neo4jstub/conf/neo4j-wrapper.conf
src/p01/neo4jstub/conf/neo4j.properties
src/p01/neo4jstub/conf/windows-wrapper-logging.properties
src/p01/neo4jstub/conf/ssl/snakeoil.cert
src/p01/neo4jstub/conf/ssl/snakeoil.key
src/p01/neo4jstub/tests/__init__.py
src/p01/neo4jstub/tests/tests.py